[
    {
        "comment": "посла",
        "contact": "NikolayUlyanov@yandex.ru",
        "created_at": "2023-11-05 18:25:07",
        "desc": "&amp;lt;div class=&amp;quot;block-container mobile-px&amp;quot; galleries=&amp;quot;&amp;quot;&amp;gt;&amp;lt;h1&amp;gt;Ремонт квартир в Москве&amp;lt;\/h1&amp;gt;&amp;lt;p&amp;gt;&amp;lt;strong&amp;gt;Компания REMCRAFT&amp;lt;\/strong&amp;gt; выполняет качественный ремонт квартир в Москве и Московской области. Спектр наших услуг, опыт и профессионализм мастеров, а также компетенции руководителей проектов позволяют с высоким качеством провести абсолютно все внутренние отделочные работы в вашей квартире силами одного подрядчика.&amp;lt;\/p&amp;gt;&amp;lt;\/div&amp;gt;",
        "id": 1,
        "ip": "172.18.0.1",
        "name": "Николай",
        "status": "не рассмотрена",
        "updated_at": "2023-11-05 18:35:29"
    },
    {
        "comment": null,
        "contact": "8-495-737 11 55",
        "created_at": "2023-11-05 18:27:07",
        "desc": "",
        "id": 2,
        "ip": "172.18.0.1",
        "name": "Вася",
        "status": "рассмотрена",
        "updated_at": "2023-11-06 07:38:02"
    },
    {
        "comment": "написал на почту",
        "contact": "kulmanovskayaVK@yandex.ru",
        "created_at": "2023-11-05 18:29:23",
        "desc": "Здравствуйте!\n основу нашей деятельности заложена японская система непрерывных улучшений «Кайдзен». Эту стратегию небольших шагов, ведущих к постоянному совершенствованию, мы внедрили в 2009 году. Благодаря регулярному следованию циклу PDCA\/PDSA (с англ. «Plan-Do-Check-Act» - планирование - действие - проверка - корректировка) мы мгновенно реагируем на изменения и корректируем ошибки. А система Управления бизнес-процессами (англ. Business Process Management) позволила нам существенно повысить качество управления и контроля.",
        "id": 6,
        "ip": "172.18.0.1",
        "name": "Елена Викторовна Кульмановская",
        "status": "рассмотрена",
        "updated_at": "2023-11-05 19:06:19"
    },
    {
        "comment": "позвонил",
        "contact": "459 743-15-21",
        "created_at": "2023-11-05 18:30:39",
        "desc": "Позвоните мне",
        "id": 8,
        "ip": "172.18.0.1",
        "name": "Василий",
        "status": "рассмотрена",
        "updated_at": "2023-11-05 18:50:00"
    },
    {
        "comment": null,
        "contact": "petr@mail.ru",
        "created_at": "2023-11-05 18:51:04",
        "desc": "Требуется ремонт квартиры!",
        "id": 9,
        "ip": "172.18.0.1",
        "name": "Петр",
        "status": "не рассмотрена",
        "updated_at": "2023-11-05 18:51:04"
    },
    {
        "comment": null,
        "contact": "vp@mail.ru",
        "created_at": "2023-11-05 19:18:17",
        "desc": "",
        "id": 12,
        "ip": "172.18.0.1",
        "name": "Виктор Петрович",
        "status": "не рассмотрена",
        "updated_at": "2023-11-05 19:18:17"
    },
    {
        "comment": null,
        "contact": "1111111111111",
        "created_at": "2023-11-07 08:10:04",
        "desc": "",
        "id": 13,
        "ip": "172.18.0.1",
        "name": "wetwety",
        "status": "не рассмотрена",
        "updated_at": "2023-11-07 08:10:04"
    },
    {
        "comment": null,
        "contact": "11111111111111",
        "created_at": "2023-11-07 08:14:22",
        "desc": "",
        "id": 16,
        "ip": "172.18.0.1",
        "name": "etwetwt",
        "status": "не рассмотрена",
        "updated_at": "2023-11-07 08:14:22"
    },
    {
        "comment": null,
        "contact": "wwef@ya.ru",
        "created_at": "2023-11-07 08:16:39",
        "desc": "Заявка",
        "id": 18,
        "ip": "172.18.0.1",
        "name": "Николай",
        "status": "не рассмотрена",
        "updated_at": "2023-11-07 08:16:39"
    }
]